ThesisAZsc/Main.py
ThesisAZsc/Model_Selection.py
ThesisAZsc/PredictionModule.py
ThesisAZsc/__init__.py
ThesisAZsc/preprocessing.py
ThesisAZsc/Model/__init__.py
ThesisAZsc/Model/keras_metadata.pb
ThesisAZsc/Model/saved_model.pb
ThesisAZsc/Model/assets/__init__.py
ThesisAZsc/Model/variables/__init__.py
ThesisAZsc/Model/variables/variables.data-00000-of-00001
ThesisAZsc/Model/variables/variables.index
ThesisAZsc-0.0.9.dist-info/METADATA
ThesisAZsc-0.0.9.dist-info/WHEEL
ThesisAZsc-0.0.9.dist-info/top_level.txt
ThesisAZsc-0.0.9.dist-info/RECORD
