Metadata-Version: 2.1
Name: ThesisAZsc
Version: 0.0.9
Summary: test file
Author: Aman and Akanksha
Author-email: <mail@neuralnine.com>
License: UNKNOWN
Keywords: python,Alzheimers,Diagnosis,Single cell,Genomics
Platform: UNKNOWN
Classifier: Development Status :: 1 - Planning
Classifier: Intended Audience :: Developers
Classifier: Programming Language :: Python :: 3
Classifier: Operating System :: Unix
Classifier: Operating System :: MacOS :: MacOS X
Classifier: Operating System :: Microsoft :: Windows
Requires-Dist: pandas
Requires-Dist: numpy
Requires-Dist: tensorflow
Requires-Dist: keras
